lexer/__init__.py
lexer/core.py
lexer/main.py
lexer_fdfattor_2025-1.0.1.dist-info/METADATA
lexer_fdfattor_2025-1.0.1.dist-info/WHEEL
lexer_fdfattor_2025-1.0.1.dist-info/top_level.txt
lexer_fdfattor_2025-1.0.1.dist-info/RECORD
