Metadata-Version: 2.4
Name: lexer-fdfattor-2025
Version: 1.0.1
Summary: Lexer - TP1 de Sintaxis
Author: FDFattor
License: MIT
Project-URL: Homepage, https://pypi.org/project/lexer-fdfattor-2025/
Keywords: lexer,syntax,parser,compiler
Classifier: Development Status :: 4 - Beta
Classifier: Intended Audience :: Education
Classifier: License :: OSI Approved :: MIT License
Classifier: Programming Language :: Python :: 3
Classifier: Programming Language :: Python :: 3.8
Classifier: Programming Language :: Python :: 3.9
Classifier: Programming Language :: Python :: 3.10
Classifier: Programming Language :: Python :: 3.11
Classifier: Programming Language :: Python :: 3.12
Classifier: Programming Language :: Python :: 3.13
Requires-Python: >=3.8
